pdbsharp/IOarea.py
pdbsharp/__init__.py
pdbsharp/attachedpane.py
pdbsharp/attachedpane.tcss
pdbsharp/debuginputarea.py
pdbsharp/debugresponsearea.py
pdbsharp/detachedpane.py
pdbsharp/detachedpane.tcss
pdbsharp/dummy.py
pdbsharp/messages.py
pdbsharp/pdbsharp.py
pdbsharp/process_utils.py
pdbsharp/resizebar.py
pdbsharp/styles.tcss
pdbsharp/wrappedclient.py
pdbsharp/wrappedtabpane.py
pdbsharp-0.5.3.dist-info/WHEEL
pdbsharp-0.5.3.dist-info/entry_points.txt
pdbsharp-0.5.3.dist-info/METADATA
pdbsharp-0.5.3.dist-info/RECORD
