Metadata-Version: 2.3
Name: pdbsharp
Version: 0.5.3
Summary: A TUI frontend for pdb
Classifier: Development Status :: 2 - Pre-Alpha
Classifier: Environment :: Console
Classifier: Topic :: Software Development :: Debuggers
Requires-Dist: psutil>=7.0.0
Requires-Dist: textual>=5.2.0
Requires-Python: >=3.14
Project-URL: Issues, https://github.com/JeffersGlass/pdbsharp.issues
Project-URL: Repository, https://github.com/JeffersGlass/pdbsharp.git
